odoo10_addon_mgmtsystem_quality-10.0.1.0.0-py2.7-nspkg.pth
odoo/addons/mgmtsystem_quality/README.rst
odoo/addons/mgmtsystem_quality/__init__.py
odoo/addons/mgmtsystem_quality/__manifest__.py
odoo/addons/mgmtsystem_quality/data/mgmtsystem_system.xml
odoo/addons/mgmtsystem_quality/i18n/de.po
odoo/addons/mgmtsystem_quality/i18n/fr.po
odoo/addons/mgmtsystem_quality/i18n/mgmtsystem_quality.pot
odoo/addons/mgmtsystem_quality/i18n/nb.po
odoo/addons/mgmtsystem_quality/i18n/pt_BR.po
odoo/addons/mgmtsystem_quality/i18n/sv.po
odoo/addons/mgmtsystem_quality/i18n/vi.po
odoo/addons/mgmtsystem_quality/static/description/icon.png
odoo10_addon_mgmtsystem_quality-10.0.1.0.0.dist-info/DESCRIPTION.rst
odoo10_addon_mgmtsystem_quality-10.0.1.0.0.dist-info/METADATA
odoo10_addon_mgmtsystem_quality-10.0.1.0.0.dist-info/RECORD
odoo10_addon_mgmtsystem_quality-10.0.1.0.0.dist-info/WHEEL
odoo10_addon_mgmtsystem_quality-10.0.1.0.0.dist-info/metadata.json
odoo10_addon_mgmtsystem_quality-10.0.1.0.0.dist-info/namespace_packages.txt
odoo10_addon_mgmtsystem_quality-10.0.1.0.0.dist-info/top_level.txt
