Metadata-Version: 2.0
Name: odoo10-addon-mgmtsystem-quality
Version: 10.0.1.0.0
Summary: Quality Management System
Home-page: http://www.savoirfairelinux.com
Author: Savoir-faire Linux, Odoo Community Association (OCA)
Author-email: support@odoo-community.org
License: AGPL-3
Platform: UNKNOWN
Classifier: Programming Language :: Python :: 2.7
Classifier: Framework :: Odoo
Classifier: License :: OSI Approved :: GNU Affero General Public License v3
Requires-Dist: odoo (<10.1dev,>=10.0)
Requires-Dist: odoo10-addon-document-page-quality-manual
Requires-Dist: odoo10-addon-mgmtsystem-audit
Requires-Dist: odoo10-addon-mgmtsystem-review
